brforest/__init__.py
brforest/brforest.py
brforest-1.0.1.dist-info/LICENSE
brforest-1.0.1.dist-info/METADATA
brforest-1.0.1.dist-info/WHEEL
brforest-1.0.1.dist-info/top_level.txt
brforest-1.0.1.dist-info/RECORD
