Metadata-Version: 2.1
Name: brforest
Version: 1.0.1
Summary: Scikit compatible implementation of random forests with bayesian vote aggregation introduced in "Decision-forest voting scheme for classification of rare classes in network intrusion detection" by Brabec and Machlica at IEEE SMC 2018
Home-page: https://github.com/JanBrabec/brforest
Author: Jan Brabec
Author-email: brabecjan91@gmail.com
License: UNKNOWN
Platform: UNKNOWN
License-File: LICENSE
Requires-Dist: numpy (<2,>=1.20.3)
Requires-Dist: scikit-learn (<2,>=0.24.2)
